code2read/__init__.py
code2read/__main__ .py
code2read/code.py
code2read-0.2.2.0.dist-info/METADATA
code2read-0.2.2.0.dist-info/RECORD
code2read-0.2.2.0.dist-info/WHEEL
code2read-0.2.2.0.dist-info/entry_points.txt
code2read-0.2.2.0.dist-info/top_level.txt
