Metadata-Version: 2.1
Name: code2read
Version: 0.2.2.0
Summary: Converts your code with comments into a workable README.md: Code more. Write less.
Home-page: https://github.com/SubhadityaMukherjee/code_to_readme
Author: Subhaditya Mukherjee
Author-email: mukherjeesubhaditya001@gmail.com
License: MIT
Platform: UNKNOWN
